indentation_converter/__init__.py
indentation_converter/indentation_converter.py
indentation_converter-0.1.0.dist-info/LICENSE
indentation_converter-0.1.0.dist-info/METADATA
indentation_converter-0.1.0.dist-info/WHEEL
indentation_converter-0.1.0.dist-info/RECORD
