Metadata-Version: 2.1
Name: indentation-converter
Version: 0.1.0
Summary: Convert indentation between spaces and tabs in text files and directories, ignoring hidden files, binary files, and files in `.gitiginore`.
Home-page: https://github.com/HenestrosaDev/indentation-converter
License: MIT
Keywords: indentation,tabs,spaces,converter
Author: HenestrosaDev
Author-email: henestrosadev@gmail.com
Requires-Python: >=3.9,<4.0
Classifier: Environment :: Console
Classifier: Intended Audience :: Developers
Classifier: License :: OSI Approved :: MIT License
Classifier: Operating System :: MacOS
Classifier: Operating System :: Microsoft :: Windows
Classifier: Operating System :: OS Independent
Classifier: Operating System :: Other OS
Classifier: Operating System :: POSIX :: Linux
Classifier: Programming Language :: Python :: 3
Classifier: Programming Language :: Python :: 3.9
Classifier: Programming Language :: Python :: 3.10
Classifier: Programming Language :: Python :: 3.11
Classifier: Programming Language :: Python :: 3.12
Classifier: Topic :: Text Processing :: General
Classifier: Topic :: Utilities
Requires-Dist: binaryornot (>=0.4.4,<0.5.0)
Requires-Dist: pathspec (>=0.12.1,<0.13.0)
Project-URL: Repository, https://github.com/HenestrosaDev/indentation-converter
